gradle.properties
hexdoc_slate_work/__gradle_version__.py
hexdoc_slate_work/__init__.py
hexdoc_slate_work/__version__.py
hexdoc_slate_work/_hooks.py
hexdoc_slate_work/py.typed
hexdoc_slate_work/_export/.gitignore
hexdoc_slate_work/_export/__init__.py
hexdoc_slate_work/_export/generated/__init__.py
hexdoc_slate_work/_export/generated/slate_work.hexdoc.json
hexdoc_slate_work/_export/generated/slate_work.patterns.hexdoc.json
hexdoc_slate_work/_export/generated/assets/hexcasting/patchouli_books/thehexbook/en_us/entries/casting/loci.json
hexdoc_slate_work/_export/generated/assets/hexcasting/patchouli_books/thehexbook/en_us/entries/greatwork/accelerator_loci.json
hexdoc_slate_work/_export/generated/assets/hexcasting/patchouli_books/thehexbook/en_us/entries/greatwork/akashic_loci.json
hexdoc_slate_work/_export/generated/assets/hexcasting/patchouli_books/thehexbook/en_us/entries/greatwork/ambit_loci.json
hexdoc_slate_work/_export/generated/assets/hexcasting/patchouli_books/thehexbook/en_us/entries/greatwork/broadcaster_loci.json
hexdoc_slate_work/_export/generated/assets/hexcasting/patchouli_books/thehexbook/en_us/entries/greatwork/crafting_loci.json
hexdoc_slate_work/_export/generated/assets/hexcasting/patchouli_books/thehexbook/en_us/entries/greatwork/hotbar_loci.json
hexdoc_slate_work/_export/generated/assets/hexcasting/patchouli_books/thehexbook/en_us/entries/greatwork/listener_impetus.json
hexdoc_slate_work/_export/generated/assets/hexcasting/patchouli_books/thehexbook/en_us/entries/greatwork/macro_loci.json
hexdoc_slate_work/_export/generated/assets/hexcasting/patchouli_books/thehexbook/en_us/entries/greatwork/mute_loci.json
hexdoc_slate_work/_export/generated/assets/hexcasting/patchouli_books/thehexbook/en_us/entries/greatwork/redstone_loci.json
hexdoc_slate_work/_export/generated/assets/hexcasting/patchouli_books/thehexbook/en_us/entries/greatwork/save_loci.json
hexdoc_slate_work-1.0.7.1.0.dist-info/METADATA
hexdoc_slate_work-1.0.7.1.0.dist-info/WHEEL
hexdoc_slate_work-1.0.7.1.0.dist-info/entry_points.txt
hexdoc_slate_work-1.0.7.1.0.dist-info/licenses/LICENSE.txt
hexdoc_slate_work-1.0.7.1.0.dist-info/RECORD
