Metadata-Version: 2.4
Name: hexdoc-slate-work
Version: 1.0.7.1.0
Summary: hexdoc plugin for Slate Work's web book.
Project-URL: Homepage, https://stick404.github.io/SlateWork/
Project-URL: Source, https://github.com/Stick404/SlateWork
Author: Stick404
License-File: LICENSE.txt
Keywords: hexdoc
Requires-Python: >=3.11
Requires-Dist: hexdoc-hexcasting~=0.11.2.1.0.dev20
Requires-Dist: hexdoc-hexpose~=1.0.0.1.0.dev0
Provides-Extra: dev
Requires-Dist: ruff~=0.11.2; extra == 'dev'
